README.md
setup.py
pycodegraph/__init__.py
pycodegraph/cli.py
pycodegraph.egg-info/PKG-INFO
pycodegraph.egg-info/SOURCES.txt
pycodegraph.egg-info/dependency_links.txt
pycodegraph.egg-info/entry_points.txt
pycodegraph.egg-info/requires.txt
pycodegraph.egg-info/top_level.txt
pycodegraph/analysis/__init__.py
pycodegraph/analysis/imports.py
pycodegraph/renderers/__init__.py
pycodegraph/renderers/graphviz.py