Metadata-Version: 2.1
Name: pycodegraph
Version: 0.1.3
Summary: Analyze and make graphs from Python code.
Home-page: https://github.com/anlutro/pycodegraph
Author: Andreas Lutro
Author-email: anlutro@gmail.com
License: GPL-3.0
Platform: UNKNOWN
